scholr/__init__.py
scholr/core.py
scholr/parser.py
scholr/utils.py
scholr-0.2.3.dist-info/licenses/LICENSE
scholr-0.2.3.dist-info/METADATA
scholr-0.2.3.dist-info/WHEEL
scholr-0.2.3.dist-info/top_level.txt
scholr-0.2.3.dist-info/RECORD
