Metadata-Version: 2.4
Name: scholr
Version: 0.2.3
Summary: A lightweight scraper for Google Scholar
Home-page: https://github.com/An4s0/Scholr
Author: Anas AlMutary
Author-email: me@ianas.me
Classifier: Programming Language :: Python :: 3
Classifier: License :: OSI Approved :: MIT License
Requires-Python: >=3.7
License-File: LICENSE
Requires-Dist: beautifulsoup4
Requires-Dist: requests
Dynamic: author
Dynamic: author-email
Dynamic: classifier
Dynamic: description
Dynamic: description-content-type
Dynamic: home-page
Dynamic: license-file
Dynamic: requires-dist
Dynamic: requires-python
Dynamic: summary
